[
  {
    "id": "#INV2540",
    "order_by": "Michael A. Miner",
    "items": ["T-shirt", "Wallet"],
    "purchase_status": "Items Received",
    "date": "07 Jan, 2023",
    "total": "$621",
    "payment_method": "Mastercard",
    "payment_status": "Completed"
  },
  {
    "id": "#INV3924",
    "order_by": "Theresa T. Brose",
    "items": ["Golden Dress", "Sunglass"],
    "purchase_status": "Items Received",
    "date": "03 Dec, 2023",
    "total": "$502",
    "payment_method": "Visa",
    "payment_status": "Cancel"
  },
  {
    "id": "#INV5032",
    "order_by": "James L. Erickson",
    "items": ["Shoes", "Cargo Pent"],
    "purchase_status": "Items Received",
    "date": "28 Sep, 2023",
    "total": "$218",
    "payment_method": "Paypal",
    "payment_status": "Completed"
  },
  {
    "id": "#INV1695",
    "order_by": "Lily W. Wilson",
    "items": ["Watch", "T-shirt"],
    "purchase_status": "Items Received",
    "date": "10 Aug, 2023",
    "total": "$428",
    "payment_method": "Mastercard",
    "payment_status": "Pending"
  },
  {
    "id": "#INV8473",
    "order_by": "Sarah M. Brooks",
    "items": ["Hand Bag", "Watch"],
    "purchase_status": "Items Received",
    "date": "22 May, 2023",
    "total": "$314",
    "payment_method": "Visa",
    "payment_status": "Cancel"
  },
  {
    "id": "#INV2150",
    "order_by": "Joe K. Hall",
    "items": ["Headphone", "Dress"],
    "purchase_status": "Items Received",
    "date": "15 Mar, 2023",
    "total": "$591",
    "payment_method": "Paypal",
    "payment_status": "Completed"
  },
  {
    "id": "#INV5636",
    "order_by": "Ralph Hueber",
    "items": ["Headphone"],
    "purchase_status": "Items Received",
    "date": "19 Dec, 2023",
    "total": "$815",
    "payment_method": "Visa",
    "payment_status": "Completed"
  },
  {
    "id": "#INV2940",
    "order_by": "Sarah Drescher",
    "items": ["Cap", "Sunglass", "Hand Bag"],
    "purchase_status": "Items Received",
    "date": "11 Jun, 2023",
    "total": "$715",
    "payment_method": "Mastercard",
    "payment_status": "Completed"
  },
  {
    "id": "#INV9027",
    "order_by": "Leonie Meister",
    "items": ["Headphone", "T-shirt"],
    "purchase_status": "Items Received",
    "date": "19 Mar, 2023",
    "total": "$351",
    "payment_method": "Paypal",
    "payment_status": "Pending"
  }
]
